bokeh_django/__init__.py
bokeh_django/apps.py
bokeh_django/consumers.py
bokeh_django/routing.py
bokeh_django/static.py
bokeh_django-0.2.1.dist-info/licenses/LICENSE
bokeh_django-0.2.1.dist-info/METADATA
bokeh_django-0.2.1.dist-info/WHEEL
bokeh_django-0.2.1.dist-info/top_level.txt
bokeh_django-0.2.1.dist-info/RECORD
