Metadata-Version: 2.4
Name: bokeh-django
Version: 0.2.1
Summary: Utility to integrate Bokeh with Django Channels
Author-email: Bokeh Team <info@bokeh.org>
Project-URL: Homepage, https://github.com/bokeh/bokeh-django
Keywords: Bokeh,Django,Channels,web,visualization
Classifier: License :: OSI Approved :: BSD License
Classifier: Programming Language :: Python
Classifier: Programming Language :: Python :: 3
Requires-Python: >=3.7
License-File: LICENSE
Requires-Dist: bokeh
Requires-Dist: django
Requires-Dist: channels
Dynamic: license-file
